{
    "Meta Data": {
        "1. Information": "Daily Prices (open, high, low, close) and Volumes",
        "2. Symbol": "BGNE",
        "3. Last Refreshed": "2017-11-22",
        "4. Output Size": "Full size",
        "5. Time Zone": "US/Eastern"
    },
    "Time Series (Daily)": {
        "2017-11-22": {
            "1. open": "85.5000",
            "2. high": "86.3000",
            "3. low": "84.0000",
            "4. close": "86.0800",
            "5. volume": "137482"
        },
        "2017-11-21": {
            "1. open": "85.1300",
            "2. high": "85.4920",
            "3. low": "83.4500",
            "4. close": "85.0400",
            "5. volume": "221621"
        },
        "2017-11-20": {
            "1. open": "84.9000",
            "2. high": "87.7900",
            "3. low": "84.3200",
            "4. close": "84.8700",
            "5. volume": "240961"
        },
        "2017-11-17": {
            "1. open": "84.4100",
            "2. high": "84.4400",
            "3. low": "82.5010",
            "4. close": "84.1800",
            "5. volume": "152564"
        },
        "2017-11-16": {
            "1. open": "81.1000",
            "2. high": "86.2450",
            "3. low": "80.5950",
            "4. close": "84.6900",
            "5. volume": "252485"
        },
        "2017-11-15": {
            "1. open": "78.7000",
            "2. high": "80.8400",
            "3. low": "78.6700",
            "4. close": "80.4300",
            "5. volume": "353677"
        },
        "2017-11-14": {
            "1. open": "81.5000",
            "2. high": "82.0000",
            "3. low": "78.6150",
            "4. close": "79.6000",
            "5. volume": "628470"
        },
        "2017-11-13": {
            "1. open": "83.9500",
            "2. high": "84.2120",
            "3. low": "82.0300",
            "4. close": "83.1800",
            "5. volume": "193900"
        },
        "2017-11-10": {
            "1. open": "83.1800",
            "2. high": "84.6000",
            "3. low": "81.4900",
            "4. close": "84.2200",
            "5. volume": "137133"
        },
        "2017-11-09": {
            "1. open": "81.6200",
            "2. high": "83.9800",
            "3. low": "80.9000",
            "4. close": "82.9600",
            "5. volume": "164491"
        },
        "2017-11-08": {
            "1. open": "87.4400",
            "2. high": "88.0000",
            "3. low": "80.5600",
            "4. close": "81.6200",
            "5. volume": "185870"
        },
        "2017-11-07": {
            "1. open": "88.5000",
            "2. high": "89.1700",
            "3. low": "86.1000",
            "4. close": "87.2800",
            "5. volume": "239277"
        },
        "2017-11-06": {
            "1. open": "92.3800",
            "2. high": "92.3900",
            "3. low": "86.9900",
            "4. close": "88.3200",
            "5. volume": "326182"
        },
        "2017-11-03": {
            "1. open": "89.2600",
            "2. high": "92.1900",
            "3. low": "87.7700",
            "4. close": "90.2300",
            "5. volume": "259444"
        },
        "2017-11-02": {
            "1. open": "89.0000",
            "2. high": "90.8500",
            "3. low": "86.7600",
            "4. close": "89.3700",
            "5. volume": "290415"
        },
        "2017-11-01": {
            "1. open": "93.3900",
            "2. high": "93.3900",
            "3. low": "88.3500",
            "4. close": "88.9300",
            "5. volume": "392557"
        },
        "2017-10-31": {
            "1. open": "88.4100",
            "2. high": "92.6900",
            "3. low": "86.0110",
            "4. close": "92.3000",
            "5. volume": "536622"
        },
        "2017-10-30": {
            "1. open": "81.0000",
            "2. high": "90.5800",
            "3. low": "81.0000",
            "4. close": "88.0000",
            "5. volume": "422883"
        },
        "2017-10-27": {
            "1. open": "80.0000",
            "2. high": "82.5500",
            "3. low": "79.1620",
            "4. close": "82.3500",
            "5. volume": "224847"
        },
        "2017-10-26": {
            "1. open": "81.8100",
            "2. high": "81.8100",
            "3. low": "79.0300",
            "4. close": "80.0100",
            "5. volume": "242446"
        },
        "2017-10-25": {
            "1. open": "84.3000",
            "2. high": "87.4900",
            "3. low": "81.1000",
            "4. close": "81.8100",
            "5. volume": "335826"
        },
        "2017-10-24": {
            "1. open": "81.5200",
            "2. high": "84.8090",
            "3. low": "80.2800",
            "4. close": "84.3000",
            "5. volume": "266418"
        },
        "2017-10-23": {
            "1. open": "84.3700",
            "2. high": "85.0650",
            "3. low": "80.1300",
            "4. close": "81.5100",
            "5. volume": "402204"
        },
        "2017-10-20": {
            "1. open": "84.2000",
            "2. high": "84.9750",
            "3. low": "82.1800",
            "4. close": "84.0300",
            "5. volume": "312758"
        },
        "2017-10-19": {
            "1. open": "88.2600",
            "2. high": "88.3300",
            "3. low": "80.5000",
            "4. close": "84.2300",
            "5. volume": "662759"
        },
        "2017-10-18": {
            "1. open": "88.2500",
            "2. high": "89.9200",
            "3. low": "85.5300",
            "4. close": "88.3000",
            "5. volume": "403058"
        },
        "2017-10-17": {
            "1. open": "92.6000",
            "2. high": "93.7000",
            "3. low": "87.1500",
            "4. close": "87.6600",
            "5. volume": "478019"
        },
        "2017-10-16": {
            "1. open": "94.5000",
            "2. high": "96.5490",
            "3. low": "91.0500",
            "4. close": "93.7200",
            "5. volume": "322359"
        },
        "2017-10-13": {
            "1. open": "96.9100",
            "2. high": "98.4600",
            "3. low": "93.5500",
            "4. close": "94.3600",
            "5. volume": "301867"
        },
        "2017-10-12": {
            "1. open": "107.4400",
            "2. high": "107.4400",
            "3. low": "95.0000",
            "4. close": "96.0700",
            "5. volume": "740253"
        },
        "2017-10-11": {
            "1. open": "113.6600",
            "2. high": "114.0800",
            "3. low": "105.2600",
            "4. close": "108.0500",
            "5. volume": "394679"
        },
        "2017-10-10": {
            "1. open": "113.5400",
            "2. high": "118.9500",
            "3. low": "113.0400",
            "4. close": "114.7300",
            "5. volume": "613739"
        },
        "2017-10-09": {
            "1. open": "105.0000",
            "2. high": "114.7200",
            "3. low": "105.0000",
            "4. close": "113.2900",
            "5. volume": "354206"
        },
        "2017-10-06": {
            "1. open": "109.0000",
            "2. high": "109.0600",
            "3. low": "103.4700",
            "4. close": "103.8400",
            "5. volume": "200636"
        },
        "2017-10-05": {
            "1. open": "111.0000",
            "2. high": "111.9990",
            "3. low": "108.6200",
            "4. close": "109.0500",
            "5. volume": "164337"
        },
        "2017-10-04": {
            "1. open": "105.0000",
            "2. high": "111.9900",
            "3. low": "104.9100",
            "4. close": "110.5800",
            "5. volume": "268583"
        },
        "2017-10-03": {
            "1. open": "102.3900",
            "2. high": "105.6400",
            "3. low": "100.1800",
            "4. close": "105.0300",
            "5. volume": "119544"
        },
        "2017-10-02": {
            "1. open": "104.2700",
            "2. high": "106.9990",
            "3. low": "99.7900",
            "4. close": "102.3900",
            "5. volume": "239242"
        },
        "2017-09-29": {
            "1. open": "96.3000",
            "2. high": "103.7990",
            "3. low": "96.3000",
            "4. close": "103.4600",
            "5. volume": "296147"
        },
        "2017-09-28": {
            "1. open": "101.3100",
            "2. high": "102.0000",
            "3. low": "91.5900",
            "4. close": "97.4300",
            "5. volume": "353250"
        },
        "2017-09-27": {
            "1. open": "87.9500",
            "2. high": "100.9900",
            "3. low": "87.6600",
            "4. close": "100.0400",
            "5. volume": "650626"
        },
        "2017-09-26": {
            "1. open": "84.6800",
            "2. high": "88.2000",
            "3. low": "84.5790",
            "4. close": "87.5100",
            "5. volume": "146091"
        },
        "2017-09-25": {
            "1. open": "85.6500",
            "2. high": "85.6500",
            "3. low": "81.7700",
            "4. close": "85.2600",
            "5. volume": "206551"
        },
        "2017-09-22": {
            "1. open": "84.9800",
            "2. high": "85.9700",
            "3. low": "83.6100",
            "4. close": "85.1400",
            "5. volume": "230623"
        },
        "2017-09-21": {
            "1. open": "86.0100",
            "2. high": "86.8000",
            "3. low": "84.0000",
            "4. close": "84.8900",
            "5. volume": "137059"
        },
        "2017-09-20": {
            "1. open": "84.1600",
            "2. high": "87.7700",
            "3. low": "82.3200",
            "4. close": "86.2500",
            "5. volume": "312954"
        },
        "2017-09-19": {
            "1. open": "83.3200",
            "2. high": "85.8180",
            "3. low": "82.0100",
            "4. close": "85.1400",
            "5. volume": "136805"
        },
        "2017-09-18": {
            "1. open": "80.9000",
            "2. high": "85.5500",
            "3. low": "80.7700",
            "4. close": "82.7700",
            "5. volume": "214852"
        },
        "2017-09-15": {
            "1. open": "76.6900",
            "2. high": "84.7300",
            "3. low": "76.6900",
            "4. close": "80.9000",
            "5. volume": "653637"
        },
        "2017-09-14": {
            "1. open": "75.0000",
            "2. high": "76.8900",
            "3. low": "73.6100",
            "4. close": "75.9900",
            "5. volume": "131201"
        },
        "2017-09-13": {
            "1. open": "70.3600",
            "2. high": "75.7400",
            "3. low": "70.2070",
            "4. close": "75.6100",
            "5. volume": "173350"
        },
        "2017-09-12": {
            "1. open": "69.3300",
            "2. high": "71.0000",
            "3. low": "69.0000",
            "4. close": "70.6200",
            "5. volume": "129094"
        },
        "2017-09-11": {
            "1. open": "72.6000",
            "2. high": "74.0500",
            "3. low": "69.6100",
            "4. close": "70.1000",
            "5. volume": "182077"
        },
        "2017-09-08": {
            "1. open": "74.5300",
            "2. high": "74.5300",
            "3. low": "72.2600",
            "4. close": "72.6000",
            "5. volume": "135393"
        },
        "2017-09-07": {
            "1. open": "76.2300",
            "2. high": "77.9400",
            "3. low": "74.5400",
            "4. close": "74.8100",
            "5. volume": "150772"
        },
        "2017-09-06": {
            "1. open": "74.0400",
            "2. high": "78.5080",
            "3. low": "73.2700",
            "4. close": "76.6600",
            "5. volume": "147438"
        },
        "2017-09-05": {
            "1. open": "75.5100",
            "2. high": "76.8400",
            "3. low": "72.6000",
            "4. close": "73.9000",
            "5. volume": "210842"
        },
        "2017-09-01": {
            "1. open": "69.4500",
            "2. high": "76.1360",
            "3. low": "69.2850",
            "4. close": "75.1800",
            "5. volume": "322091"
        },
        "2017-08-31": {
            "1. open": "69.4800",
            "2. high": "69.8381",
            "3. low": "66.8805",
            "4. close": "68.9200",
            "5. volume": "404051"
        },
        "2017-08-30": {
            "1. open": "69.3800",
            "2. high": "70.4500",
            "3. low": "68.6900",
            "4. close": "68.8600",
            "5. volume": "172609"
        },
        "2017-08-29": {
            "1. open": "67.0200",
            "2. high": "70.4800",
            "3. low": "66.8400",
            "4. close": "69.4800",
            "5. volume": "239189"
        },
        "2017-08-28": {
            "1. open": "69.2400",
            "2. high": "70.7130",
            "3. low": "68.0150",
            "4. close": "68.6700",
            "5. volume": "169380"
        },
        "2017-08-25": {
            "1. open": "70.5800",
            "2. high": "70.5800",
            "3. low": "67.5290",
            "4. close": "68.8100",
            "5. volume": "83940"
        },
        "2017-08-24": {
            "1. open": "69.4100",
            "2. high": "70.2800",
            "3. low": "69.0700",
            "4. close": "69.9300",
            "5. volume": "152792"
        },
        "2017-08-23": {
            "1. open": "69.4100",
            "2. high": "71.3400",
            "3. low": "68.4950",
            "4. close": "68.7600",
            "5. volume": "96135"
        },
        "2017-08-22": {
            "1. open": "66.7500",
            "2. high": "70.1700",
            "3. low": "65.6670",
            "4. close": "70.0300",
            "5. volume": "227552"
        },
        "2017-08-21": {
            "1. open": "66.0000",
            "2. high": "68.6600",
            "3. low": "66.0000",
            "4. close": "66.8600",
            "5. volume": "153446"
        },
        "2017-08-18": {
            "1. open": "68.3500",
            "2. high": "68.3500",
            "3. low": "65.5850",
            "4. close": "66.1900",
            "5. volume": "249907"
        },
        "2017-08-17": {
            "1. open": "69.9700",
            "2. high": "71.9200",
            "3. low": "68.8410",
            "4. close": "69.2100",
            "5. volume": "99623"
        },
        "2017-08-16": {
            "1. open": "70.4200",
            "2. high": "71.3500",
            "3. low": "69.4300",
            "4. close": "70.0200",
            "5. volume": "304990"
        },
        "2017-08-15": {
            "1. open": "71.5500",
            "2. high": "72.6938",
            "3. low": "68.8000",
            "4. close": "69.9700",
            "5. volume": "559311"
        },
        "2017-08-14": {
            "1. open": "72.0100",
            "2. high": "72.0100",
            "3. low": "70.5000",
            "4. close": "71.3500",
            "5. volume": "414317"
        },
        "2017-08-11": {
            "1. open": "74.3700",
            "2. high": "74.3700",
            "3. low": "71.0000",
            "4. close": "71.0200",
            "5. volume": "770293"
        },
        "2017-08-10": {
            "1. open": "74.2700",
            "2. high": "76.0000",
            "3. low": "71.6600",
            "4. close": "72.6400",
            "5. volume": "509817"
        },
        "2017-08-09": {
            "1. open": "78.1800",
            "2. high": "79.8050",
            "3. low": "77.0200",
            "4. close": "77.3000",
            "5. volume": "100165"
        },
        "2017-08-08": {
            "1. open": "77.7900",
            "2. high": "79.8900",
            "3. low": "77.0000",
            "4. close": "78.4000",
            "5. volume": "144582"
        },
        "2017-08-07": {
            "1. open": "73.3300",
            "2. high": "78.7800",
            "3. low": "73.1090",
            "4. close": "77.3600",
            "5. volume": "295695"
        },
        "2017-08-04": {
            "1. open": "71.6300",
            "2. high": "73.9900",
            "3. low": "70.0000",
            "4. close": "72.3100",
            "5. volume": "66569"
        },
        "2017-08-03": {
            "1. open": "70.8900",
            "2. high": "72.2950",
            "3. low": "69.7900",
            "4. close": "71.6100",
            "5. volume": "111228"
        },
        "2017-08-02": {
            "1. open": "72.5200",
            "2. high": "72.9400",
            "3. low": "68.6100",
            "4. close": "70.8600",
            "5. volume": "172690"
        },
        "2017-08-01": {
            "1. open": "71.1400",
            "2. high": "72.8450",
            "3. low": "70.0100",
            "4. close": "72.5300",
            "5. volume": "275526"
        },
        "2017-07-31": {
            "1. open": "72.5700",
            "2. high": "73.9500",
            "3. low": "70.4200",
            "4. close": "70.4900",
            "5. volume": "123421"
        },
        "2017-07-28": {
            "1. open": "70.6000",
            "2. high": "73.5000",
            "3. low": "69.5050",
            "4. close": "72.5400",
            "5. volume": "254828"
        },
        "2017-07-27": {
            "1. open": "71.3700",
            "2. high": "73.4800",
            "3. low": "70.8400",
            "4. close": "71.0000",
            "5. volume": "213250"
        },
        "2017-07-26": {
            "1. open": "69.7400",
            "2. high": "71.9400",
            "3. low": "69.7000",
            "4. close": "71.2300",
            "5. volume": "215889"
        },
        "2017-07-25": {
            "1. open": "73.8200",
            "2. high": "75.0080",
            "3. low": "68.5200",
            "4. close": "69.6000",
            "5. volume": "380838"
        },
        "2017-07-24": {
            "1. open": "77.4900",
            "2. high": "77.4900",
            "3. low": "71.3000",
            "4. close": "73.5000",
            "5. volume": "687197"
        },
        "2017-07-21": {
            "1. open": "78.0100",
            "2. high": "79.0000",
            "3. low": "76.9300",
            "4. close": "77.2900",
            "5. volume": "309380"
        },
        "2017-07-20": {
            "1. open": "77.2000",
            "2. high": "79.2500",
            "3. low": "77.0600",
            "4. close": "77.6000",
            "5. volume": "225890"
        },
        "2017-07-19": {
            "1. open": "76.5200",
            "2. high": "77.9200",
            "3. low": "75.9500",
            "4. close": "77.0100",
            "5. volume": "195233"
        },
        "2017-07-18": {
            "1. open": "75.5700",
            "2. high": "77.5100",
            "3. low": "75.5000",
            "4. close": "76.5700",
            "5. volume": "267084"
        },
        "2017-07-17": {
            "1. open": "73.9600",
            "2. high": "75.9900",
            "3. low": "73.5500",
            "4. close": "75.6000",
            "5. volume": "268606"
        },
        "2017-07-14": {
            "1. open": "72.0900",
            "2. high": "74.1000",
            "3. low": "71.8100",
            "4. close": "73.6900",
            "5. volume": "122990"
        },
        "2017-07-13": {
            "1. open": "73.0000",
            "2. high": "73.0000",
            "3. low": "71.0000",
            "4. close": "72.3600",
            "5. volume": "213996"
        },
        "2017-07-12": {
            "1. open": "74.3700",
            "2. high": "74.3700",
            "3. low": "70.8800",
            "4. close": "72.8600",
            "5. volume": "307920"
        },
        "2017-07-11": {
            "1. open": "70.5300",
            "2. high": "76.1200",
            "3. low": "70.4000",
            "4. close": "73.8900",
            "5. volume": "529499"
        },
        "2017-07-10": {
            "1. open": "70.3600",
            "2. high": "72.8300",
            "3. low": "69.3800",
            "4. close": "70.8500",
            "5. volume": "487323"
        },
        "2017-07-07": {
            "1. open": "66.7000",
            "2. high": "70.4500",
            "3. low": "66.1800",
            "4. close": "70.1800",
            "5. volume": "709272"
        },
        "2017-07-06": {
            "1. open": "61.0600",
            "2. high": "68.6700",
            "3. low": "60.0000",
            "4. close": "66.2800",
            "5. volume": "2474507"
        },
        "2017-07-05": {
            "1. open": "54.0000",
            "2. high": "54.5858",
            "3. low": "50.6300",
            "4. close": "52.2700",
            "5. volume": "388811"
        },
        "2017-07-03": {
            "1. open": "45.2100",
            "2. high": "54.4700",
            "3. low": "45.2100",
            "4. close": "54.3600",
            "5. volume": "211606"
        },
        "2017-06-30": {
            "1. open": "45.2400",
            "2. high": "45.5391",
            "3. low": "44.7450",
            "4. close": "45.0000",
            "5. volume": "60890"
        },
        "2017-06-29": {
            "1. open": "45.5100",
            "2. high": "45.9450",
            "3. low": "44.5600",
            "4. close": "44.8700",
            "5. volume": "230350"
        },
        "2017-06-28": {
            "1. open": "45.5300",
            "2. high": "45.8700",
            "3. low": "44.4500",
            "4. close": "45.5100",
            "5. volume": "113135"
        },
        "2017-06-27": {
            "1. open": "45.4400",
            "2. high": "45.6500",
            "3. low": "44.7450",
            "4. close": "45.3100",
            "5. volume": "74956"
        },
        "2017-06-26": {
            "1. open": "45.0100",
            "2. high": "45.5700",
            "3. low": "44.2300",
            "4. close": "45.5500",
            "5. volume": "81086"
        },
        "2017-06-23": {
            "1. open": "44.2700",
            "2. high": "46.0000",
            "3. low": "43.0800",
            "4. close": "44.8500",
            "5. volume": "209578"
        },
        "2017-06-22": {
            "1. open": "45.0000",
            "2. high": "45.0000",
            "3. low": "43.2040",
            "4. close": "44.3900",
            "5. volume": "179603"
        },
        "2017-06-21": {
            "1. open": "43.0000",
            "2. high": "45.0000",
            "3. low": "42.9900",
            "4. close": "44.8800",
            "5. volume": "167356"
        },
        "2017-06-20": {
            "1. open": "43.5000",
            "2. high": "43.7500",
            "3. low": "42.9500",
            "4. close": "43.0100",
            "5. volume": "90536"
        },
        "2017-06-19": {
            "1. open": "41.7600",
            "2. high": "44.0450",
            "3. low": "41.7400",
            "4. close": "43.3500",
            "5. volume": "111453"
        },
        "2017-06-16": {
            "1. open": "39.6900",
            "2. high": "41.7200",
            "3. low": "38.1400",
            "4. close": "41.5600",
            "5. volume": "133777"
        },
        "2017-06-15": {
            "1. open": "39.6500",
            "2. high": "39.9800",
            "3. low": "38.8000",
            "4. close": "39.5000",
            "5. volume": "52874"
        },
        "2017-06-14": {
            "1. open": "39.7200",
            "2. high": "40.0000",
            "3. low": "39.2500",
            "4. close": "39.6800",
            "5. volume": "31465"
        },
        "2017-06-13": {
            "1. open": "39.2300",
            "2. high": "40.6900",
            "3. low": "38.6700",
            "4. close": "39.5300",
            "5. volume": "30579"
        },
        "2017-06-12": {
            "1. open": "39.0200",
            "2. high": "39.8000",
            "3. low": "38.6227",
            "4. close": "39.0000",
            "5. volume": "40966"
        },
        "2017-06-09": {
            "1. open": "38.7900",
            "2. high": "40.1600",
            "3. low": "38.5200",
            "4. close": "38.9100",
            "5. volume": "83221"
        },
        "2017-06-08": {
            "1. open": "39.4100",
            "2. high": "39.7600",
            "3. low": "38.2500",
            "4. close": "38.6800",
            "5. volume": "73303"
        },
        "2017-06-07": {
            "1. open": "38.9000",
            "2. high": "39.9900",
            "3. low": "38.6650",
            "4. close": "39.3900",
            "5. volume": "103676"
        },
        "2017-06-06": {
            "1. open": "40.3000",
            "2. high": "41.0400",
            "3. low": "38.9200",
            "4. close": "39.2200",
            "5. volume": "29279"
        },
        "2017-06-05": {
            "1. open": "41.1300",
            "2. high": "42.2756",
            "3. low": "40.1900",
            "4. close": "40.4300",
            "5. volume": "58967"
        },
        "2017-06-02": {
            "1. open": "38.3700",
            "2. high": "41.2000",
            "3. low": "38.0100",
            "4. close": "41.0100",
            "5. volume": "89110"
        },
        "2017-06-01": {
            "1. open": "36.7800",
            "2. high": "38.3600",
            "3. low": "36.7500",
            "4. close": "38.2000",
            "5. volume": "26757"
        },
        "2017-05-31": {
            "1. open": "37.4900",
            "2. high": "37.6448",
            "3. low": "36.5100",
            "4. close": "36.7500",
            "5. volume": "51318"
        },
        "2017-05-30": {
            "1. open": "37.3300",
            "2. high": "38.3400",
            "3. low": "36.8400",
            "4. close": "37.4300",
            "5. volume": "140808"
        },
        "2017-05-26": {
            "1. open": "37.5600",
            "2. high": "37.8383",
            "3. low": "36.8300",
            "4. close": "37.4200",
            "5. volume": "118879"
        },
        "2017-05-25": {
            "1. open": "38.3100",
            "2. high": "38.3453",
            "3. low": "37.3100",
            "4. close": "37.4600",
            "5. volume": "39048"
        },
        "2017-05-24": {
            "1. open": "36.8400",
            "2. high": "38.4300",
            "3. low": "36.8100",
            "4. close": "38.4000",
            "5. volume": "74972"
        },
        "2017-05-23": {
            "1. open": "37.6200",
            "2. high": "37.7500",
            "3. low": "36.7200",
            "4. close": "36.8200",
            "5. volume": "30084"
        },
        "2017-05-22": {
            "1. open": "36.9100",
            "2. high": "37.9300",
            "3. low": "36.9100",
            "4. close": "37.5500",
            "5. volume": "94025"
        },
        "2017-05-19": {
            "1. open": "38.6000",
            "2. high": "39.2000",
            "3. low": "36.8000",
            "4. close": "36.9400",
            "5. volume": "140339"
        },
        "2017-05-18": {
            "1. open": "38.8400",
            "2. high": "38.8423",
            "3. low": "37.2410",
            "4. close": "38.5100",
            "5. volume": "103449"
        },
        "2017-05-17": {
            "1. open": "37.5300",
            "2. high": "39.0000",
            "3. low": "37.5300",
            "4. close": "38.7400",
            "5. volume": "108623"
        },
        "2017-05-16": {
            "1. open": "37.6300",
            "2. high": "38.6700",
            "3. low": "37.3010",
            "4. close": "37.9400",
            "5. volume": "44065"
        },
        "2017-05-15": {
            "1. open": "36.7100",
            "2. high": "37.8100",
            "3. low": "36.7100",
            "4. close": "37.7200",
            "5. volume": "48366"
        },
        "2017-05-12": {
            "1. open": "37.0400",
            "2. high": "37.2300",
            "3. low": "36.3200",
            "4. close": "36.4900",
            "5. volume": "55245"
        },
        "2017-05-11": {
            "1. open": "37.7200",
            "2. high": "37.8500",
            "3. low": "34.3600",
            "4. close": "36.9500",
            "5. volume": "166553"
        },
        "2017-05-10": {
            "1. open": "37.8400",
            "2. high": "38.4100",
            "3. low": "37.0900",
            "4. close": "37.9500",
            "5. volume": "93593"
        },
        "2017-05-09": {
            "1. open": "38.6400",
            "2. high": "39.7400",
            "3. low": "36.7500",
            "4. close": "37.4400",
            "5. volume": "164154"
        },
        "2017-05-08": {
            "1. open": "39.7500",
            "2. high": "39.9000",
            "3. low": "38.2850",
            "4. close": "38.7200",
            "5. volume": "59028"
        },
        "2017-05-05": {
            "1. open": "40.2300",
            "2. high": "40.2300",
            "3. low": "38.9500",
            "4. close": "39.3000",
            "5. volume": "52431"
        },
        "2017-05-04": {
            "1. open": "41.0000",
            "2. high": "41.3600",
            "3. low": "39.3500",
            "4. close": "39.7500",
            "5. volume": "295673"
        },
        "2017-05-03": {
            "1. open": "40.4100",
            "2. high": "41.1500",
            "3. low": "40.2600",
            "4. close": "40.6200",
            "5. volume": "48678"
        },
        "2017-05-02": {
            "1. open": "40.7000",
            "2. high": "40.8000",
            "3. low": "40.5800",
            "4. close": "40.6100",
            "5. volume": "89426"
        },
        "2017-05-01": {
            "1. open": "40.8400",
            "2. high": "42.0900",
            "3. low": "38.8620",
            "4. close": "40.6400",
            "5. volume": "59704"
        },
        "2017-04-28": {
            "1. open": "40.7700",
            "2. high": "40.9400",
            "3. low": "40.4000",
            "4. close": "40.8800",
            "5. volume": "92522"
        },
        "2017-04-27": {
            "1. open": "40.0000",
            "2. high": "40.7800",
            "3. low": "38.6500",
            "4. close": "40.5900",
            "5. volume": "195955"
        },
        "2017-04-26": {
            "1. open": "39.2300",
            "2. high": "40.3700",
            "3. low": "39.2200",
            "4. close": "40.1100",
            "5. volume": "96124"
        },
        "2017-04-25": {
            "1. open": "37.8100",
            "2. high": "39.4600",
            "3. low": "37.8100",
            "4. close": "39.1800",
            "5. volume": "84431"
        },
        "2017-04-24": {
            "1. open": "37.2400",
            "2. high": "37.7600",
            "3. low": "36.6600",
            "4. close": "37.6100",
            "5. volume": "73987"
        },
        "2017-04-21": {
            "1. open": "36.8800",
            "2. high": "37.0800",
            "3. low": "36.5075",
            "4. close": "36.7100",
            "5. volume": "80276"
        },
        "2017-04-20": {
            "1. open": "37.0900",
            "2. high": "37.1200",
            "3. low": "36.4100",
            "4. close": "36.9800",
            "5. volume": "70638"
        },
        "2017-04-19": {
            "1. open": "36.9300",
            "2. high": "37.1000",
            "3. low": "36.5300",
            "4. close": "36.8300",
            "5. volume": "64151"
        },
        "2017-04-18": {
            "1. open": "38.1300",
            "2. high": "38.2539",
            "3. low": "36.6050",
            "4. close": "36.8600",
            "5. volume": "29617"
        },
        "2017-04-17": {
            "1. open": "38.1100",
            "2. high": "38.6360",
            "3. low": "37.8400",
            "4. close": "38.3000",
            "5. volume": "38486"
        },
        "2017-04-13": {
            "1. open": "37.9000",
            "2. high": "38.5400",
            "3. low": "37.6500",
            "4. close": "37.9000",
            "5. volume": "87772"
        },
        "2017-04-12": {
            "1. open": "38.4000",
            "2. high": "38.4103",
            "3. low": "37.6350",
            "4. close": "38.0700",
            "5. volume": "29383"
        },
        "2017-04-11": {
            "1. open": "37.7600",
            "2. high": "38.4500",
            "3. low": "37.1000",
            "4. close": "38.3300",
            "5. volume": "59260"
        },
        "2017-04-10": {
            "1. open": "37.1000",
            "2. high": "38.4400",
            "3. low": "37.1000",
            "4. close": "37.8100",
            "5. volume": "40343"
        },
        "2017-04-07": {
            "1. open": "36.7200",
            "2. high": "37.5300",
            "3. low": "36.1042",
            "4. close": "37.2200",
            "5. volume": "98476"
        },
        "2017-04-06": {
            "1. open": "36.6800",
            "2. high": "37.7500",
            "3. low": "36.3150",
            "4. close": "37.0300",
            "5. volume": "185119"
        },
        "2017-04-05": {
            "1. open": "37.0300",
            "2. high": "37.8300",
            "3. low": "35.9200",
            "4. close": "36.4800",
            "5. volume": "229392"
        },
        "2017-04-04": {
            "1. open": "36.5100",
            "2. high": "37.5500",
            "3. low": "36.5100",
            "4. close": "37.2200",
            "5. volume": "69487"
        },
        "2017-04-03": {
            "1. open": "36.8700",
            "2. high": "37.4800",
            "3. low": "36.5800",
            "4. close": "36.6100",
            "5. volume": "64092"
        },
        "2017-03-31": {
            "1. open": "36.5800",
            "2. high": "37.1700",
            "3. low": "36.4000",
            "4. close": "36.6100",
            "5. volume": "99911"
        },
        "2017-03-30": {
            "1. open": "36.6900",
            "2. high": "36.9900",
            "3. low": "36.2600",
            "4. close": "36.5900",
            "5. volume": "154033"
        },
        "2017-03-29": {
            "1. open": "36.3000",
            "2. high": "37.4590",
            "3. low": "36.3000",
            "4. close": "36.7950",
            "5. volume": "80193"
        },
        "2017-03-28": {
            "1. open": "36.4200",
            "2. high": "36.9000",
            "3. low": "35.6700",
            "4. close": "36.2100",
            "5. volume": "161450"
        },
        "2017-03-27": {
            "1. open": "35.9100",
            "2. high": "36.6100",
            "3. low": "35.3030",
            "4. close": "36.3200",
            "5. volume": "129123"
        },
        "2017-03-24": {
            "1. open": "37.3400",
            "2. high": "37.6300",
            "3. low": "36.1100",
            "4. close": "36.3000",
            "5. volume": "199536"
        },
        "2017-03-23": {
            "1. open": "37.7500",
            "2. high": "37.9750",
            "3. low": "36.7600",
            "4. close": "36.8200",
            "5. volume": "127643"
        },
        "2017-03-22": {
            "1. open": "38.0600",
            "2. high": "38.2500",
            "3. low": "37.5200",
            "4. close": "38.0000",
            "5. volume": "94160"
        },
        "2017-03-21": {
            "1. open": "39.7400",
            "2. high": "40.1800",
            "3. low": "37.7000",
            "4. close": "37.8900",
            "5. volume": "114332"
        },
        "2017-03-20": {
            "1. open": "39.6600",
            "2. high": "40.2000",
            "3. low": "38.8500",
            "4. close": "39.5600",
            "5. volume": "95629"
        },
        "2017-03-17": {
            "1. open": "38.7900",
            "2. high": "40.1900",
            "3. low": "38.7900",
            "4. close": "39.5500",
            "5. volume": "92975"
        },
        "2017-03-16": {
            "1. open": "39.2600",
            "2. high": "39.8300",
            "3. low": "38.2550",
            "4. close": "39.0700",
            "5. volume": "102421"
        },
        "2017-03-15": {
            "1. open": "39.4800",
            "2. high": "39.9800",
            "3. low": "39.4100",
            "4. close": "39.7900",
            "5. volume": "114573"
        },
        "2017-03-14": {
            "1. open": "39.6100",
            "2. high": "39.8100",
            "3. low": "39.0000",
            "4. close": "39.2300",
            "5. volume": "38748"
        },
        "2017-03-13": {
            "1. open": "39.9900",
            "2. high": "40.1100",
            "3. low": "39.3600",
            "4. close": "39.6500",
            "5. volume": "60309"
        },
        "2017-03-10": {
            "1. open": "40.0000",
            "2. high": "40.0800",
            "3. low": "39.6800",
            "4. close": "39.9900",
            "5. volume": "44342"
        },
        "2017-03-09": {
            "1. open": "39.8800",
            "2. high": "40.1800",
            "3. low": "39.3700",
            "4. close": "39.6400",
            "5. volume": "109543"
        },
        "2017-03-08": {
            "1. open": "39.5200",
            "2. high": "40.1100",
            "3. low": "38.6960",
            "4. close": "39.8800",
            "5. volume": "52333"
        },
        "2017-03-07": {
            "1. open": "39.8200",
            "2. high": "40.1400",
            "3. low": "39.1300",
            "4. close": "39.5500",
            "5. volume": "52116"
        },
        "2017-03-06": {
            "1. open": "40.5900",
            "2. high": "41.0800",
            "3. low": "39.1600",
            "4. close": "39.8200",
            "5. volume": "159882"
        },
        "2017-03-03": {
            "1. open": "40.1500",
            "2. high": "41.2700",
            "3. low": "39.9200",
            "4. close": "40.7700",
            "5. volume": "285515"
        },
        "2017-03-02": {
            "1. open": "40.0500",
            "2. high": "41.8900",
            "3. low": "39.7900",
            "4. close": "40.1000",
            "5. volume": "257744"
        },
        "2017-03-01": {
            "1. open": "39.4100",
            "2. high": "40.7050",
            "3. low": "39.4100",
            "4. close": "40.4200",
            "5. volume": "143358"
        },
        "2017-02-28": {
            "1. open": "38.1300",
            "2. high": "40.9400",
            "3. low": "38.1300",
            "4. close": "38.9700",
            "5. volume": "101172"
        },
        "2017-02-27": {
            "1. open": "38.5000",
            "2. high": "38.5000",
            "3. low": "37.7610",
            "4. close": "38.0600",
            "5. volume": "57583"
        },
        "2017-02-24": {
            "1. open": "37.7900",
            "2. high": "38.8700",
            "3. low": "37.4200",
            "4. close": "38.5700",
            "5. volume": "90055"
        },
        "2017-02-23": {
            "1. open": "39.7900",
            "2. high": "39.7900",
            "3. low": "37.7000",
            "4. close": "37.9100",
            "5. volume": "69537"
        },
        "2017-02-22": {
            "1. open": "39.4600",
            "2. high": "40.1300",
            "3. low": "39.1350",
            "4. close": "39.7500",
            "5. volume": "55686"
        },
        "2017-02-21": {
            "1. open": "40.8700",
            "2. high": "40.8700",
            "3. low": "39.1400",
            "4. close": "39.7000",
            "5. volume": "107767"
        },
        "2017-02-17": {
            "1. open": "40.8800",
            "2. high": "41.0000",
            "3. low": "40.1700",
            "4. close": "40.7500",
            "5. volume": "52093"
        },
        "2017-02-16": {
            "1. open": "40.0000",
            "2. high": "40.9800",
            "3. low": "39.5100",
            "4. close": "40.7800",
            "5. volume": "229614"
        },
        "2017-02-15": {
            "1. open": "37.8400",
            "2. high": "41.0000",
            "3. low": "37.3910",
            "4. close": "40.4300",
            "5. volume": "263589"
        },
        "2017-02-14": {
            "1. open": "36.1400",
            "2. high": "37.8100",
            "3. low": "36.0700",
            "4. close": "37.6300",
            "5. volume": "275422"
        },
        "2017-02-13": {
            "1. open": "36.0000",
            "2. high": "36.2600",
            "3. low": "35.6600",
            "4. close": "36.0600",
            "5. volume": "60832"
        },
        "2017-02-10": {
            "1. open": "35.5200",
            "2. high": "36.2900",
            "3. low": "35.3200",
            "4. close": "36.0000",
            "5. volume": "78653"
        },
        "2017-02-09": {
            "1. open": "36.3600",
            "2. high": "36.4800",
            "3. low": "35.3400",
            "4. close": "35.3500",
            "5. volume": "58307"
        },
        "2017-02-08": {
            "1. open": "35.0200",
            "2. high": "36.3450",
            "3. low": "34.5200",
            "4. close": "36.1100",
            "5. volume": "141673"
        },
        "2017-02-07": {
            "1. open": "36.1700",
            "2. high": "36.1700",
            "3. low": "34.2850",
            "4. close": "34.7300",
            "5. volume": "71693"
        },
        "2017-02-06": {
            "1. open": "36.0000",
            "2. high": "36.0350",
            "3. low": "35.5050",
            "4. close": "35.9200",
            "5. volume": "67219"
        },
        "2017-02-03": {
            "1. open": "36.3400",
            "2. high": "36.3900",
            "3. low": "35.4800",
            "4. close": "35.8800",
            "5. volume": "53983"
        },
        "2017-02-02": {
            "1. open": "36.4500",
            "2. high": "36.4500",
            "3. low": "35.5000",
            "4. close": "36.0300",
            "5. volume": "43246"
        },
        "2017-02-01": {
            "1. open": "35.2900",
            "2. high": "36.0000",
            "3. low": "34.8200",
            "4. close": "36.0000",
            "5. volume": "26142"
        },
        "2017-01-31": {
            "1. open": "33.7700",
            "2. high": "35.1300",
            "3. low": "33.6400",
            "4. close": "34.8400",
            "5. volume": "20132"
        },
        "2017-01-30": {
            "1. open": "35.2800",
            "2. high": "35.9400",
            "3. low": "33.5100",
            "4. close": "34.1100",
            "5. volume": "108403"
        },
        "2017-01-27": {
            "1. open": "36.0000",
            "2. high": "36.6550",
            "3. low": "35.8200",
            "4. close": "36.3500",
            "5. volume": "68241"
        },
        "2017-01-26": {
            "1. open": "35.3200",
            "2. high": "36.4400",
            "3. low": "34.7200",
            "4. close": "35.8200",
            "5. volume": "127126"
        },
        "2017-01-25": {
            "1. open": "32.8600",
            "2. high": "36.0000",
            "3. low": "32.8600",
            "4. close": "35.7200",
            "5. volume": "137503"
        },
        "2017-01-24": {
            "1. open": "32.3409",
            "2. high": "33.3450",
            "3. low": "32.3409",
            "4. close": "33.0000",
            "5. volume": "74560"
        },
        "2017-01-23": {
            "1. open": "32.3495",
            "2. high": "32.6000",
            "3. low": "31.9000",
            "4. close": "32.3900",
            "5. volume": "22914"
        },
        "2017-01-20": {
            "1. open": "32.5000",
            "2. high": "32.7800",
            "3. low": "31.7400",
            "4. close": "32.0100",
            "5. volume": "34380"
        },
        "2017-01-19": {
            "1. open": "32.6000",
            "2. high": "32.9300",
            "3. low": "31.7900",
            "4. close": "32.4600",
            "5. volume": "26706"
        },
        "2017-01-18": {
            "1. open": "33.0000",
            "2. high": "33.0000",
            "3. low": "32.2400",
            "4. close": "32.8000",
            "5. volume": "72679"
        },
        "2017-01-17": {
            "1. open": "32.4900",
            "2. high": "32.9800",
            "3. low": "31.7000",
            "4. close": "32.8900",
            "5. volume": "47904"
        },
        "2017-01-13": {
            "1. open": "31.9000",
            "2. high": "32.9500",
            "3. low": "31.9000",
            "4. close": "32.6900",
            "5. volume": "42889"
        },
        "2017-01-12": {
            "1. open": "31.1700",
            "2. high": "32.2000",
            "3. low": "31.0000",
            "4. close": "31.8500",
            "5. volume": "76522"
        },
        "2017-01-11": {
            "1. open": "31.3800",
            "2. high": "31.6600",
            "3. low": "30.6700",
            "4. close": "31.3000",
            "5. volume": "48980"
        },
        "2017-01-10": {
            "1. open": "31.5300",
            "2. high": "31.7800",
            "3. low": "31.0700",
            "4. close": "31.4900",
            "5. volume": "38605"
        },
        "2017-01-09": {
            "1. open": "30.9300",
            "2. high": "31.8532",
            "3. low": "30.3700",
            "4. close": "31.5300",
            "5. volume": "62613"
        },
        "2017-01-06": {
            "1. open": "31.1900",
            "2. high": "31.2400",
            "3. low": "30.3700",
            "4. close": "30.8100",
            "5. volume": "33425"
        },
        "2017-01-05": {
            "1. open": "31.7500",
            "2. high": "31.9600",
            "3. low": "30.0207",
            "4. close": "31.0200",
            "5. volume": "112460"
        },
        "2017-01-04": {
            "1. open": "30.5900",
            "2. high": "32.1800",
            "3. low": "30.5900",
            "4. close": "31.7700",
            "5. volume": "88680"
        },
        "2017-01-03": {
            "1. open": "30.6315",
            "2. high": "31.0700",
            "3. low": "29.5810",
            "4. close": "31.0500",
            "5. volume": "72353"
        },
        "2016-12-30": {
            "1. open": "29.3200",
            "2. high": "30.9100",
            "3. low": "29.0600",
            "4. close": "30.3600",
            "5. volume": "92658"
        },
        "2016-12-29": {
            "1. open": "29.4200",
            "2. high": "30.0200",
            "3. low": "29.1000",
            "4. close": "29.1700",
            "5. volume": "53646"
        },
        "2016-12-28": {
            "1. open": "29.4400",
            "2. high": "30.1200",
            "3. low": "29.3800",
            "4. close": "29.7200",
            "5. volume": "31297"
        },
        "2016-12-27": {
            "1. open": "30.1100",
            "2. high": "30.9300",
            "3. low": "29.3400",
            "4. close": "29.5900",
            "5. volume": "56755"
        },
        "2016-12-23": {
            "1. open": "29.0000",
            "2. high": "30.1700",
            "3. low": "29.0000",
            "4. close": "30.0100",
            "5. volume": "79979"
        },
        "2016-12-22": {
            "1. open": "28.6500",
            "2. high": "29.2400",
            "3. low": "28.3900",
            "4. close": "28.9200",
            "5. volume": "107337"
        },
        "2016-12-21": {
            "1. open": "28.0500",
            "2. high": "28.9800",
            "3. low": "27.8900",
            "4. close": "28.6400",
            "5. volume": "195339"
        },
        "2016-12-20": {
            "1. open": "29.2700",
            "2. high": "29.6350",
            "3. low": "27.9100",
            "4. close": "28.1200",
            "5. volume": "143173"
        },
        "2016-12-19": {
            "1. open": "29.7400",
            "2. high": "29.8650",
            "3. low": "29.0500",
            "4. close": "29.2300",
            "5. volume": "121104"
        },
        "2016-12-16": {
            "1. open": "29.8700",
            "2. high": "30.3000",
            "3. low": "29.2503",
            "4. close": "29.6100",
            "5. volume": "594556"
        },
        "2016-12-15": {
            "1. open": "28.6600",
            "2. high": "29.9000",
            "3. low": "28.3200",
            "4. close": "29.7700",
            "5. volume": "145707"
        },
        "2016-12-14": {
            "1. open": "29.6300",
            "2. high": "29.9700",
            "3. low": "28.2000",
            "4. close": "28.9500",
            "5. volume": "181788"
        },
        "2016-12-13": {
            "1. open": "28.5700",
            "2. high": "29.6700",
            "3. low": "28.3500",
            "4. close": "29.3400",
            "5. volume": "191163"
        },
        "2016-12-12": {
            "1. open": "27.4600",
            "2. high": "28.6600",
            "3. low": "27.2900",
            "4. close": "28.6100",
            "5. volume": "181660"
        },
        "2016-12-09": {
            "1. open": "27.0200",
            "2. high": "27.5700",
            "3. low": "26.7100",
            "4. close": "27.2000",
            "5. volume": "196030"
        },
        "2016-12-08": {
            "1. open": "27.9200",
            "2. high": "27.9200",
            "3. low": "26.4300",
            "4. close": "26.9500",
            "5. volume": "190270"
        },
        "2016-12-07": {
            "1. open": "27.9700",
            "2. high": "28.2650",
            "3. low": "26.7100",
            "4. close": "27.9300",
            "5. volume": "306589"
        },
        "2016-12-06": {
            "1. open": "28.5000",
            "2. high": "30.2262",
            "3. low": "27.6000",
            "4. close": "27.9700",
            "5. volume": "263325"
        },
        "2016-12-05": {
            "1. open": "31.2100",
            "2. high": "31.4425",
            "3. low": "28.2100",
            "4. close": "28.3100",
            "5. volume": "157418"
        },
        "2016-12-02": {
            "1. open": "30.5700",
            "2. high": "31.4300",
            "3. low": "30.5000",
            "4. close": "30.8600",
            "5. volume": "103668"
        },
        "2016-12-01": {
            "1. open": "31.6000",
            "2. high": "31.9350",
            "3. low": "30.4800",
            "4. close": "30.8000",
            "5. volume": "97588"
        },
        "2016-11-30": {
            "1. open": "31.7900",
            "2. high": "31.9700",
            "3. low": "31.0000",
            "4. close": "31.7000",
            "5. volume": "123833"
        },
        "2016-11-29": {
            "1. open": "31.0700",
            "2. high": "31.8900",
            "3. low": "31.0675",
            "4. close": "31.5900",
            "5. volume": "112432"
        },
        "2016-11-28": {
            "1. open": "32.2700",
            "2. high": "32.8500",
            "3. low": "30.6400",
            "4. close": "30.8800",
            "5. volume": "113072"
        },
        "2016-11-25": {
            "1. open": "31.8900",
            "2. high": "32.7900",
            "3. low": "31.5900",
            "4. close": "32.4100",
            "5. volume": "51512"
        },
        "2016-11-23": {
            "1. open": "31.5500",
            "2. high": "32.2400",
            "3. low": "31.3100",
            "4. close": "32.0000",
            "5. volume": "118678"
        },
        "2016-11-22": {
            "1. open": "32.2400",
            "2. high": "33.2800",
            "3. low": "31.3000",
            "4. close": "31.4700",
            "5. volume": "132904"
        },
        "2016-11-21": {
            "1. open": "31.6800",
            "2. high": "32.1000",
            "3. low": "31.1000",
            "4. close": "31.5100",
            "5. volume": "220184"
        },
        "2016-11-18": {
            "1. open": "33.9500",
            "2. high": "33.9500",
            "3. low": "31.6500",
            "4. close": "32.0000",
            "5. volume": "1515581"
        },
        "2016-11-17": {
            "1. open": "32.4000",
            "2. high": "33.8600",
            "3. low": "31.2000",
            "4. close": "32.7000",
            "5. volume": "397007"
        },
        "2016-11-16": {
            "1. open": "36.1300",
            "2. high": "37.8900",
            "3. low": "36.1300",
            "4. close": "36.9000",
            "5. volume": "49084"
        },
        "2016-11-15": {
            "1. open": "34.1600",
            "2. high": "37.8500",
            "3. low": "34.1600",
            "4. close": "36.3100",
            "5. volume": "87620"
        },
        "2016-11-14": {
            "1. open": "32.3100",
            "2. high": "35.5500",
            "3. low": "32.3100",
            "4. close": "35.0500",
            "5. volume": "60375"
        },
        "2016-11-11": {
            "1. open": "35.4500",
            "2. high": "35.7400",
            "3. low": "31.8800",
            "4. close": "32.1999",
            "5. volume": "180702"
        },
        "2016-11-10": {
            "1. open": "33.9500",
            "2. high": "36.7600",
            "3. low": "32.2900",
            "4. close": "35.9200",
            "5. volume": "129067"
        },
        "2016-11-09": {
            "1. open": "32.7800",
            "2. high": "33.9500",
            "3. low": "32.7100",
            "4. close": "33.8000",
            "5. volume": "60585"
        },
        "2016-11-08": {
            "1. open": "31.5400",
            "2. high": "33.3500",
            "3. low": "31.0465",
            "4. close": "32.6000",
            "5. volume": "61805"
        },
        "2016-11-07": {
            "1. open": "31.0000",
            "2. high": "32.4000",
            "3. low": "31.0000",
            "4. close": "31.9400",
            "5. volume": "42759"
        },
        "2016-11-04": {
            "1. open": "31.3500",
            "2. high": "31.9500",
            "3. low": "31.0000",
            "4. close": "31.6000",
            "5. volume": "72218"
        },
        "2016-11-03": {
            "1. open": "33.0000",
            "2. high": "33.4951",
            "3. low": "31.0100",
            "4. close": "31.2800",
            "5. volume": "136629"
        },
        "2016-11-02": {
            "1. open": "33.4200",
            "2. high": "33.4900",
            "3. low": "32.5200",
            "4. close": "33.0600",
            "5. volume": "140241"
        },
        "2016-11-01": {
            "1. open": "33.4700",
            "2. high": "33.7500",
            "3. low": "33.0900",
            "4. close": "33.4300",
            "5. volume": "32026"
        },
        "2016-10-31": {
            "1. open": "33.4600",
            "2. high": "33.5000",
            "3. low": "32.2550",
            "4. close": "33.2400",
            "5. volume": "61050"
        },
        "2016-10-28": {
            "1. open": "32.6200",
            "2. high": "33.7200",
            "3. low": "32.3000",
            "4. close": "33.4700",
            "5. volume": "195059"
        },
        "2016-10-27": {
            "1. open": "33.1900",
            "2. high": "33.3212",
            "3. low": "32.3000",
            "4. close": "32.8100",
            "5. volume": "153100"
        },
        "2016-10-26": {
            "1. open": "32.8288",
            "2. high": "33.4300",
            "3. low": "32.6900",
            "4. close": "32.9100",
            "5. volume": "73114"
        },
        "2016-10-25": {
            "1. open": "33.2300",
            "2. high": "33.5000",
            "3. low": "33.0596",
            "4. close": "33.2700",
            "5. volume": "47967"
        },
        "2016-10-24": {
            "1. open": "32.8600",
            "2. high": "33.4700",
            "3. low": "32.8300",
            "4. close": "33.1400",
            "5. volume": "31421"
        },
        "2016-10-21": {
            "1. open": "32.6800",
            "2. high": "33.1300",
            "3. low": "32.4800",
            "4. close": "33.1300",
            "5. volume": "30756"
        },
        "2016-10-20": {
            "1. open": "32.6700",
            "2. high": "33.0400",
            "3. low": "32.5800",
            "4. close": "32.9800",
            "5. volume": "16754"
        },
        "2016-10-19": {
            "1. open": "32.9100",
            "2. high": "32.9900",
            "3. low": "32.0800",
            "4. close": "32.8300",
            "5. volume": "28936"
        },
        "2016-10-18": {
            "1. open": "32.5500",
            "2. high": "33.4800",
            "3. low": "32.3600",
            "4. close": "32.8900",
            "5. volume": "63551"
        },
        "2016-10-17": {
            "1. open": "31.4300",
            "2. high": "32.6100",
            "3. low": "31.4300",
            "4. close": "32.5300",
            "5. volume": "69724"
        },
        "2016-10-14": {
            "1. open": "32.2200",
            "2. high": "32.2450",
            "3. low": "31.4100",
            "4. close": "31.5200",
            "5. volume": "160709"
        },
        "2016-10-13": {
            "1. open": "31.2600",
            "2. high": "32.2000",
            "3. low": "30.9450",
            "4. close": "31.9600",
            "5. volume": "167322"
        },
        "2016-10-12": {
            "1. open": "32.1000",
            "2. high": "32.3401",
            "3. low": "31.2600",
            "4. close": "31.4000",
            "5. volume": "139132"
        },
        "2016-10-11": {
            "1. open": "31.9000",
            "2. high": "32.5700",
            "3. low": "31.6700",
            "4. close": "32.1800",
            "5. volume": "61026"
        },
        "2016-10-10": {
            "1. open": "31.9800",
            "2. high": "33.0970",
            "3. low": "31.1600",
            "4. close": "32.1100",
            "5. volume": "175518"
        },
        "2016-10-07": {
            "1. open": "32.0000",
            "2. high": "32.2700",
            "3. low": "31.4649",
            "4. close": "31.8400",
            "5. volume": "120623"
        },
        "2016-10-06": {
            "1. open": "31.6400",
            "2. high": "32.0500",
            "3. low": "31.3300",
            "4. close": "31.7900",
            "5. volume": "331408"
        },
        "2016-10-05": {
            "1. open": "30.9800",
            "2. high": "32.1900",
            "3. low": "30.5300",
            "4. close": "31.6800",
            "5. volume": "198480"
        },
        "2016-10-04": {
            "1. open": "31.4600",
            "2. high": "31.4800",
            "3. low": "30.3000",
            "4. close": "30.7100",
            "5. volume": "34080"
        },
        "2016-10-03": {
            "1. open": "30.8800",
            "2. high": "31.4800",
            "3. low": "30.0001",
            "4. close": "31.0000",
            "5. volume": "26060"
        },
        "2016-09-30": {
            "1. open": "29.7600",
            "2. high": "31.0900",
            "3. low": "29.7600",
            "4. close": "30.8100",
            "5. volume": "17863"
        },
        "2016-09-29": {
            "1. open": "30.2500",
            "2. high": "31.2000",
            "3. low": "29.3001",
            "4. close": "29.7200",
            "5. volume": "42857"
        },
        "2016-09-28": {
            "1. open": "29.7300",
            "2. high": "31.5900",
            "3. low": "29.5200",
            "4. close": "30.2300",
            "5. volume": "316736"
        },
        "2016-09-27": {
            "1. open": "29.3500",
            "2. high": "30.7900",
            "3. low": "29.3500",
            "4. close": "29.4900",
            "5. volume": "186803"
        },
        "2016-09-26": {
            "1. open": "30.2300",
            "2. high": "30.4400",
            "3. low": "29.0500",
            "4. close": "29.5000",
            "5. volume": "95275"
        },
        "2016-09-23": {
            "1. open": "31.3800",
            "2. high": "31.5000",
            "3. low": "30.1500",
            "4. close": "30.4900",
            "5. volume": "79609"
        },
        "2016-09-22": {
            "1. open": "31.3800",
            "2. high": "31.9400",
            "3. low": "30.9000",
            "4. close": "31.1800",
            "5. volume": "77284"
        },
        "2016-09-21": {
            "1. open": "31.3600",
            "2. high": "32.0100",
            "3. low": "30.6500",
            "4. close": "30.9800",
            "5. volume": "62927"
        },
        "2016-09-20": {
            "1. open": "31.0800",
            "2. high": "31.5900",
            "3. low": "30.5220",
            "4. close": "30.9800",
            "5. volume": "101606"
        },
        "2016-09-19": {
            "1. open": "31.3800",
            "2. high": "33.0400",
            "3. low": "30.7650",
            "4. close": "30.8900",
            "5. volume": "142109"
        },
        "2016-09-16": {
            "1. open": "32.5200",
            "2. high": "33.2800",
            "3. low": "32.3200",
            "4. close": "32.6500",
            "5. volume": "48382"
        },
        "2016-09-15": {
            "1. open": "33.8100",
            "2. high": "33.9800",
            "3. low": "32.1600",
            "4. close": "32.4500",
            "5. volume": "75654"
        },
        "2016-09-14": {
            "1. open": "31.5300",
            "2. high": "33.6392",
            "3. low": "31.1900",
            "4. close": "33.5800",
            "5. volume": "169352"
        },
        "2016-09-13": {
            "1. open": "31.5300",
            "2. high": "31.8500",
            "3. low": "31.1500",
            "4. close": "31.6700",
            "5. volume": "66984"
        },
        "2016-09-12": {
            "1. open": "30.2800",
            "2. high": "31.4800",
            "3. low": "30.2800",
            "4. close": "31.4000",
            "5. volume": "19682"
        },
        "2016-09-09": {
            "1. open": "31.1200",
            "2. high": "31.7200",
            "3. low": "30.2200",
            "4. close": "30.2800",
            "5. volume": "48403"
        },
        "2016-09-08": {
            "1. open": "29.6800",
            "2. high": "31.5800",
            "3. low": "29.6800",
            "4. close": "31.5800",
            "5. volume": "31629"
        },
        "2016-09-07": {
            "1. open": "29.4800",
            "2. high": "30.6600",
            "3. low": "29.3800",
            "4. close": "30.4500",
            "5. volume": "44842"
        },
        "2016-09-06": {
            "1. open": "29.1400",
            "2. high": "29.8700",
            "3. low": "29.1400",
            "4. close": "29.7720",
            "5. volume": "24110"
        },
        "2016-09-02": {
            "1. open": "29.4000",
            "2. high": "29.5000",
            "3. low": "29.0100",
            "4. close": "29.4900",
            "5. volume": "8730"
        },
        "2016-09-01": {
            "1. open": "28.6900",
            "2. high": "29.4600",
            "3. low": "28.4550",
            "4. close": "29.4000",
            "5. volume": "47656"
        },
        "2016-08-31": {
            "1. open": "29.0800",
            "2. high": "29.4300",
            "3. low": "28.1000",
            "4. close": "28.7100",
            "5. volume": "36727"
        },
        "2016-08-30": {
            "1. open": "28.3700",
            "2. high": "29.4600",
            "3. low": "28.2200",
            "4. close": "29.2500",
            "5. volume": "20392"
        },
        "2016-08-29": {
            "1. open": "28.2300",
            "2. high": "28.8900",
            "3. low": "27.6700",
            "4. close": "28.5300",
            "5. volume": "12495"
        },
        "2016-08-26": {
            "1. open": "27.8150",
            "2. high": "28.6300",
            "3. low": "27.8000",
            "4. close": "27.9900",
            "5. volume": "29465"
        },
        "2016-08-25": {
            "1. open": "28.3000",
            "2. high": "28.9700",
            "3. low": "27.7224",
            "4. close": "28.0000",
            "5. volume": "61589"
        },
        "2016-08-24": {
            "1. open": "29.4500",
            "2. high": "29.4500",
            "3. low": "27.8001",
            "4. close": "28.0000",
            "5. volume": "40788"
        },
        "2016-08-23": {
            "1. open": "29.0100",
            "2. high": "29.6610",
            "3. low": "28.5100",
            "4. close": "29.4100",
            "5. volume": "20797"
        },
        "2016-08-22": {
            "1. open": "29.8200",
            "2. high": "29.8200",
            "3. low": "28.5800",
            "4. close": "29.1000",
            "5. volume": "29347"
        },
        "2016-08-19": {
            "1. open": "29.4000",
            "2. high": "29.6035",
            "3. low": "28.8000",
            "4. close": "29.6000",
            "5. volume": "47713"
        },
        "2016-08-18": {
            "1. open": "28.9500",
            "2. high": "29.0400",
            "3. low": "27.8000",
            "4. close": "28.7100",
            "5. volume": "30126"
        },
        "2016-08-17": {
            "1. open": "29.1100",
            "2. high": "29.4000",
            "3. low": "27.5800",
            "4. close": "28.2200",
            "5. volume": "47881"
        },
        "2016-08-16": {
            "1. open": "28.4700",
            "2. high": "29.3700",
            "3. low": "28.3900",
            "4. close": "29.3600",
            "5. volume": "32486"
        },
        "2016-08-15": {
            "1. open": "28.3100",
            "2. high": "28.9300",
            "3. low": "27.4000",
            "4. close": "28.9300",
            "5. volume": "120970"
        },
        "2016-08-12": {
            "1. open": "27.6300",
            "2. high": "28.4800",
            "3. low": "27.5000",
            "4. close": "28.1500",
            "5. volume": "68523"
        },
        "2016-08-11": {
            "1. open": "27.6200",
            "2. high": "28.2000",
            "3. low": "27.1200",
            "4. close": "27.5000",
            "5. volume": "77645"
        },
        "2016-08-10": {
            "1. open": "27.5000",
            "2. high": "28.2400",
            "3. low": "27.4400",
            "4. close": "27.5100",
            "5. volume": "92228"
        },
        "2016-08-09": {
            "1. open": "26.7100",
            "2. high": "27.4800",
            "3. low": "26.4200",
            "4. close": "27.2900",
            "5. volume": "21723"
        },
        "2016-08-08": {
            "1. open": "26.4700",
            "2. high": "27.6900",
            "3. low": "26.4700",
            "4. close": "26.5401",
            "5. volume": "49480"
        },
        "2016-08-05": {
            "1. open": "26.3200",
            "2. high": "26.7388",
            "3. low": "26.0500",
            "4. close": "26.4900",
            "5. volume": "39409"
        },
        "2016-08-04": {
            "1. open": "26.7800",
            "2. high": "27.0422",
            "3. low": "26.0500",
            "4. close": "26.1100",
            "5. volume": "24059"
        },
        "2016-08-03": {
            "1. open": "26.2929",
            "2. high": "26.9800",
            "3. low": "25.8300",
            "4. close": "26.5900",
            "5. volume": "48346"
        },
        "2016-08-02": {
            "1. open": "25.7600",
            "2. high": "26.0000",
            "3. low": "25.5000",
            "4. close": "25.7200",
            "5. volume": "67927"
        },
        "2016-08-01": {
            "1. open": "26.0000",
            "2. high": "26.2500",
            "3. low": "24.5300",
            "4. close": "25.9300",
            "5. volume": "141784"
        },
        "2016-07-29": {
            "1. open": "27.4800",
            "2. high": "27.8280",
            "3. low": "26.2400",
            "4. close": "26.2400",
            "5. volume": "61994"
        },
        "2016-07-28": {
            "1. open": "27.4400",
            "2. high": "27.9100",
            "3. low": "26.8400",
            "4. close": "27.4000",
            "5. volume": "47458"
        },
        "2016-07-27": {
            "1. open": "27.0000",
            "2. high": "27.8000",
            "3. low": "26.8000",
            "4. close": "27.3800",
            "5. volume": "23303"
        },
        "2016-07-26": {
            "1. open": "27.0014",
            "2. high": "27.8000",
            "3. low": "26.7600",
            "4. close": "26.9100",
            "5. volume": "37237"
        },
        "2016-07-25": {
            "1. open": "27.2800",
            "2. high": "27.5300",
            "3. low": "27.0000",
            "4. close": "27.0700",
            "5. volume": "39121"
        },
        "2016-07-22": {
            "1. open": "27.7200",
            "2. high": "28.1900",
            "3. low": "27.0100",
            "4. close": "27.3000",
            "5. volume": "41468"
        },
        "2016-07-21": {
            "1. open": "29.2500",
            "2. high": "29.6220",
            "3. low": "27.4450",
            "4. close": "27.6300",
            "5. volume": "80756"
        },
        "2016-07-20": {
            "1. open": "28.1600",
            "2. high": "29.8530",
            "3. low": "28.0000",
            "4. close": "29.1200",
            "5. volume": "118981"
        },
        "2016-07-19": {
            "1. open": "28.7900",
            "2. high": "29.0700",
            "3. low": "28.0100",
            "4. close": "28.0100",
            "5. volume": "42410"
        },
        "2016-07-18": {
            "1. open": "29.3800",
            "2. high": "29.5400",
            "3. low": "28.5800",
            "4. close": "28.7300",
            "5. volume": "55188"
        },
        "2016-07-15": {
            "1. open": "29.8600",
            "2. high": "30.0000",
            "3. low": "28.3200",
            "4. close": "29.5400",
            "5. volume": "56401"
        },
        "2016-07-14": {
            "1. open": "29.7900",
            "2. high": "29.7900",
            "3. low": "28.4960",
            "4. close": "29.3900",
            "5. volume": "49208"
        },
        "2016-07-13": {
            "1. open": "29.5400",
            "2. high": "29.9600",
            "3. low": "29.3000",
            "4. close": "29.7500",
            "5. volume": "49621"
        },
        "2016-07-12": {
            "1. open": "30.0000",
            "2. high": "30.3400",
            "3. low": "28.9600",
            "4. close": "29.5000",
            "5. volume": "59376"
        },
        "2016-07-11": {
            "1. open": "29.4000",
            "2. high": "30.4783",
            "3. low": "29.1000",
            "4. close": "30.0600",
            "5. volume": "55783"
        },
        "2016-07-08": {
            "1. open": "29.0000",
            "2. high": "29.6000",
            "3. low": "28.8600",
            "4. close": "29.1800",
            "5. volume": "25753"
        },
        "2016-07-07": {
            "1. open": "28.8300",
            "2. high": "30.1995",
            "3. low": "28.8000",
            "4. close": "28.8100",
            "5. volume": "61798"
        },
        "2016-07-06": {
            "1. open": "29.0700",
            "2. high": "29.6000",
            "3. low": "28.7500",
            "4. close": "28.7500",
            "5. volume": "17147"
        },
        "2016-07-05": {
            "1. open": "29.6600",
            "2. high": "30.3460",
            "3. low": "28.9100",
            "4. close": "29.3200",
            "5. volume": "24843"
        },
        "2016-07-01": {
            "1. open": "30.0000",
            "2. high": "30.5000",
            "3. low": "29.1850",
            "4. close": "29.6400",
            "5. volume": "40822"
        },
        "2016-06-30": {
            "1. open": "30.0800",
            "2. high": "30.4300",
            "3. low": "29.1000",
            "4. close": "29.8000",
            "5. volume": "40842"
        },
        "2016-06-29": {
            "1. open": "29.2900",
            "2. high": "30.3500",
            "3. low": "28.4500",
            "4. close": "30.0300",
            "5. volume": "46741"
        },
        "2016-06-28": {
            "1. open": "28.4000",
            "2. high": "29.7100",
            "3. low": "28.1100",
            "4. close": "29.5300",
            "5. volume": "46147"
        },
        "2016-06-27": {
            "1. open": "28.2500",
            "2. high": "30.2600",
            "3. low": "28.0000",
            "4. close": "28.0000",
            "5. volume": "79769"
        },
        "2016-06-24": {
            "1. open": "29.1500",
            "2. high": "30.5000",
            "3. low": "28.1500",
            "4. close": "28.2400",
            "5. volume": "104073"
        },
        "2016-06-23": {
            "1. open": "32.0800",
            "2. high": "32.1700",
            "3. low": "30.7400",
            "4. close": "30.7400",
            "5. volume": "28810"
        },
        "2016-06-22": {
            "1. open": "31.8000",
            "2. high": "32.2600",
            "3. low": "31.0200",
            "4. close": "31.9800",
            "5. volume": "118709"
        },
        "2016-06-21": {
            "1. open": "29.8600",
            "2. high": "31.7700",
            "3. low": "27.8000",
            "4. close": "31.7700",
            "5. volume": "44185"
        },
        "2016-06-20": {
            "1. open": "31.5500",
            "2. high": "31.5500",
            "3. low": "29.6100",
            "4. close": "29.9700",
            "5. volume": "30341"
        },
        "2016-06-17": {
            "1. open": "30.2500",
            "2. high": "31.1100",
            "3. low": "29.5000",
            "4. close": "31.1000",
            "5. volume": "50657"
        },
        "2016-06-16": {
            "1. open": "29.9100",
            "2. high": "30.3500",
            "3. low": "29.1100",
            "4. close": "29.9200",
            "5. volume": "51351"
        },
        "2016-06-15": {
            "1. open": "29.9970",
            "2. high": "31.2400",
            "3. low": "29.3900",
            "4. close": "31.0500",
            "5. volume": "33626"
        },
        "2016-06-14": {
            "1. open": "29.4900",
            "2. high": "29.8900",
            "3. low": "28.4650",
            "4. close": "29.6100",
            "5. volume": "67929"
        },
        "2016-06-13": {
            "1. open": "30.8000",
            "2. high": "30.8000",
            "3. low": "29.1000",
            "4. close": "29.2200",
            "5. volume": "28825"
        },
        "2016-06-10": {
            "1. open": "30.1000",
            "2. high": "32.8000",
            "3. low": "29.0500",
            "4. close": "29.6700",
            "5. volume": "47280"
        },
        "2016-06-09": {
            "1. open": "31.4900",
            "2. high": "31.5000",
            "3. low": "30.0000",
            "4. close": "30.2700",
            "5. volume": "37168"
        },
        "2016-06-08": {
            "1. open": "32.7600",
            "2. high": "33.1899",
            "3. low": "31.4900",
            "4. close": "32.0500",
            "5. volume": "72256"
        },
        "2016-06-07": {
            "1. open": "33.2100",
            "2. high": "33.2100",
            "3. low": "32.0600",
            "4. close": "32.5300",
            "5. volume": "48851"
        },
        "2016-06-06": {
            "1. open": "31.7000",
            "2. high": "33.3100",
            "3. low": "31.6450",
            "4. close": "33.1100",
            "5. volume": "143551"
        },
        "2016-06-03": {
            "1. open": "31.0000",
            "2. high": "32.5308",
            "3. low": "29.3400",
            "4. close": "31.6900",
            "5. volume": "116064"
        },
        "2016-06-02": {
            "1. open": "29.4500",
            "2. high": "31.3700",
            "3. low": "29.4500",
            "4. close": "31.0300",
            "5. volume": "51057"
        },
        "2016-06-01": {
            "1. open": "28.3500",
            "2. high": "29.7200",
            "3. low": "28.2450",
            "4. close": "29.4600",
            "5. volume": "105271"
        },
        "2016-05-31": {
            "1. open": "27.4700",
            "2. high": "28.4499",
            "3. low": "27.4700",
            "4. close": "28.2500",
            "5. volume": "58828"
        },
        "2016-05-27": {
            "1. open": "28.4999",
            "2. high": "28.5000",
            "3. low": "27.0000",
            "4. close": "27.2600",
            "5. volume": "142331"
        },
        "2016-05-26": {
            "1. open": "27.6000",
            "2. high": "28.1000",
            "3. low": "27.5400",
            "4. close": "27.5800",
            "5. volume": "11875"
        },
        "2016-05-25": {
            "1. open": "28.0323",
            "2. high": "28.5100",
            "3. low": "27.7000",
            "4. close": "27.8300",
            "5. volume": "31937"
        },
        "2016-05-24": {
            "1. open": "27.8200",
            "2. high": "28.4150",
            "3. low": "27.0000",
            "4. close": "27.6200",
            "5. volume": "54941"
        },
        "2016-05-23": {
            "1. open": "27.1500",
            "2. high": "28.1900",
            "3. low": "27.0000",
            "4. close": "27.8200",
            "5. volume": "91529"
        },
        "2016-05-20": {
            "1. open": "27.1300",
            "2. high": "27.4300",
            "3. low": "26.7800",
            "4. close": "26.9200",
            "5. volume": "11656"
        },
        "2016-05-19": {
            "1. open": "27.3100",
            "2. high": "27.5750",
            "3. low": "26.2900",
            "4. close": "27.0900",
            "5. volume": "27501"
        },
        "2016-05-18": {
            "1. open": "27.6816",
            "2. high": "28.3000",
            "3. low": "26.7900",
            "4. close": "27.3100",
            "5. volume": "28721"
        },
        "2016-05-17": {
            "1. open": "27.5750",
            "2. high": "28.1000",
            "3. low": "26.8200",
            "4. close": "27.1000",
            "5. volume": "41400"
        },
        "2016-05-16": {
            "1. open": "27.7900",
            "2. high": "28.6500",
            "3. low": "26.8100",
            "4. close": "27.6500",
            "5. volume": "56090"
        },
        "2016-05-13": {
            "1. open": "26.7400",
            "2. high": "28.0000",
            "3. low": "26.7300",
            "4. close": "27.5000",
            "5. volume": "53535"
        },
        "2016-05-12": {
            "1. open": "28.1400",
            "2. high": "28.1400",
            "3. low": "26.6900",
            "4. close": "26.8500",
            "5. volume": "32801"
        },
        "2016-05-11": {
            "1. open": "27.7700",
            "2. high": "28.4800",
            "3. low": "27.6600",
            "4. close": "28.1900",
            "5. volume": "9326"
        },
        "2016-05-10": {
            "1. open": "27.6800",
            "2. high": "28.4700",
            "3. low": "26.6400",
            "4. close": "27.7700",
            "5. volume": "37095"
        },
        "2016-05-09": {
            "1. open": "26.2600",
            "2. high": "28.1300",
            "3. low": "26.2600",
            "4. close": "27.6700",
            "5. volume": "48388"
        },
        "2016-05-06": {
            "1. open": "26.1200",
            "2. high": "26.9700",
            "3. low": "26.0100",
            "4. close": "26.2400",
            "5. volume": "19318"
        },
        "2016-05-05": {
            "1. open": "26.5000",
            "2. high": "26.6500",
            "3. low": "26.2500",
            "4. close": "26.2500",
            "5. volume": "15632"
        },
        "2016-05-04": {
            "1. open": "26.6700",
            "2. high": "26.6700",
            "3. low": "26.0200",
            "4. close": "26.2600",
            "5. volume": "39374"
        },
        "2016-05-03": {
            "1. open": "27.2000",
            "2. high": "27.9250",
            "3. low": "26.5500",
            "4. close": "26.5500",
            "5. volume": "61669"
        },
        "2016-05-02": {
            "1. open": "27.5400",
            "2. high": "27.9400",
            "3. low": "27.0500",
            "4. close": "27.1700",
            "5. volume": "6420"
        },
        "2016-04-29": {
            "1. open": "26.5100",
            "2. high": "28.0600",
            "3. low": "26.4200",
            "4. close": "27.7600",
            "5. volume": "49806"
        },
        "2016-04-28": {
            "1. open": "27.5000",
            "2. high": "27.5000",
            "3. low": "26.0200",
            "4. close": "26.8800",
            "5. volume": "66483"
        },
        "2016-04-27": {
            "1. open": "28.8700",
            "2. high": "29.1200",
            "3. low": "26.5200",
            "4. close": "27.2700",
            "5. volume": "98465"
        },
        "2016-04-26": {
            "1. open": "29.1200",
            "2. high": "29.7200",
            "3. low": "28.5000",
            "4. close": "28.6000",
            "5. volume": "140176"
        },
        "2016-04-25": {
            "1. open": "30.1300",
            "2. high": "30.8000",
            "3. low": "28.5601",
            "4. close": "28.9700",
            "5. volume": "173410"
        },
        "2016-04-22": {
            "1. open": "29.7100",
            "2. high": "31.9450",
            "3. low": "29.2000",
            "4. close": "29.9100",
            "5. volume": "133742"
        },
        "2016-04-21": {
            "1. open": "30.2001",
            "2. high": "31.0699",
            "3. low": "28.7005",
            "4. close": "29.7100",
            "5. volume": "83968"
        },
        "2016-04-20": {
            "1. open": "31.1900",
            "2. high": "31.1900",
            "3. low": "29.9950",
            "4. close": "30.1900",
            "5. volume": "53498"
        },
        "2016-04-19": {
            "1. open": "31.5000",
            "2. high": "31.8700",
            "3. low": "30.1040",
            "4. close": "31.1600",
            "5. volume": "170952"
        },
        "2016-04-18": {
            "1. open": "31.7400",
            "2. high": "31.9800",
            "3. low": "31.0001",
            "4. close": "31.0700",
            "5. volume": "11355"
        },
        "2016-04-15": {
            "1. open": "31.1100",
            "2. high": "31.9200",
            "3. low": "30.6300",
            "4. close": "31.9200",
            "5. volume": "87959"
        },
        "2016-04-14": {
            "1. open": "31.7000",
            "2. high": "32.4300",
            "3. low": "31.0600",
            "4. close": "31.2900",
            "5. volume": "63787"
        },
        "2016-04-13": {
            "1. open": "31.5800",
            "2. high": "32.7499",
            "3. low": "31.0800",
            "4. close": "31.5400",
            "5. volume": "56172"
        },
        "2016-04-12": {
            "1. open": "31.8200",
            "2. high": "32.9800",
            "3. low": "30.8683",
            "4. close": "31.5300",
            "5. volume": "130601"
        },
        "2016-04-11": {
            "1. open": "33.1700",
            "2. high": "33.1700",
            "3. low": "30.4100",
            "4. close": "32.4600",
            "5. volume": "120133"
        },
        "2016-04-08": {
            "1. open": "31.7900",
            "2. high": "31.7900",
            "3. low": "29.5800",
            "4. close": "31.2500",
            "5. volume": "28352"
        },
        "2016-04-07": {
            "1. open": "31.2550",
            "2. high": "33.2400",
            "3. low": "29.8900",
            "4. close": "31.3000",
            "5. volume": "119522"
        },
        "2016-04-06": {
            "1. open": "29.9900",
            "2. high": "32.0000",
            "3. low": "29.5500",
            "4. close": "31.5800",
            "5. volume": "147712"
        },
        "2016-04-05": {
            "1. open": "29.2900",
            "2. high": "30.0000",
            "3. low": "28.5100",
            "4. close": "29.5100",
            "5. volume": "74742"
        },
        "2016-04-04": {
            "1. open": "28.7001",
            "2. high": "30.5000",
            "3. low": "28.7001",
            "4. close": "29.9700",
            "5. volume": "48659"
        },
        "2016-04-01": {
            "1. open": "29.1300",
            "2. high": "29.7800",
            "3. low": "28.5000",
            "4. close": "29.2100",
            "5. volume": "48244"
        },
        "2016-03-31": {
            "1. open": "28.2700",
            "2. high": "29.8800",
            "3. low": "28.2700",
            "4. close": "29.3100",
            "5. volume": "50703"
        },
        "2016-03-30": {
            "1. open": "28.0000",
            "2. high": "29.0100",
            "3. low": "28.0000",
            "4. close": "28.6000",
            "5. volume": "35380"
        },
        "2016-03-29": {
            "1. open": "27.0000",
            "2. high": "28.2400",
            "3. low": "27.0000",
            "4. close": "27.6700",
            "5. volume": "27090"
        },
        "2016-03-28": {
            "1. open": "27.9000",
            "2. high": "27.9000",
            "3. low": "26.7900",
            "4. close": "27.0300",
            "5. volume": "36003"
        },
        "2016-03-24": {
            "1. open": "26.9740",
            "2. high": "29.4450",
            "3. low": "26.9600",
            "4. close": "28.0300",
            "5. volume": "54855"
        },
        "2016-03-23": {
            "1. open": "30.9900",
            "2. high": "31.6600",
            "3. low": "27.0500",
            "4. close": "28.2500",
            "5. volume": "172646"
        },
        "2016-03-22": {
            "1. open": "29.4200",
            "2. high": "30.7900",
            "3. low": "28.7425",
            "4. close": "30.5200",
            "5. volume": "132051"
        },
        "2016-03-21": {
            "1. open": "27.0000",
            "2. high": "30.6750",
            "3. low": "27.0000",
            "4. close": "29.3000",
            "5. volume": "138215"
        },
        "2016-03-18": {
            "1. open": "26.8500",
            "2. high": "27.8100",
            "3. low": "25.2850",
            "4. close": "27.6900",
            "5. volume": "111591"
        },
        "2016-03-17": {
            "1. open": "25.8200",
            "2. high": "26.8000",
            "3. low": "25.2800",
            "4. close": "26.0300",
            "5. volume": "50019"
        },
        "2016-03-16": {
            "1. open": "26.5300",
            "2. high": "26.8900",
            "3. low": "25.5000",
            "4. close": "25.9800",
            "5. volume": "102387"
        },
        "2016-03-15": {
            "1. open": "27.0000",
            "2. high": "27.8526",
            "3. low": "26.5200",
            "4. close": "26.7800",
            "5. volume": "78345"
        },
        "2016-03-14": {
            "1. open": "28.8700",
            "2. high": "28.8700",
            "3. low": "27.0000",
            "4. close": "27.0000",
            "5. volume": "168218"
        },
        "2016-03-11": {
            "1. open": "27.9800",
            "2. high": "28.1000",
            "3. low": "26.7000",
            "4. close": "27.8800",
            "5. volume": "95609"
        },
        "2016-03-10": {
            "1. open": "29.0000",
            "2. high": "29.7100",
            "3. low": "27.1750",
            "4. close": "28.0000",
            "5. volume": "163859"
        },
        "2016-03-09": {
            "1. open": "28.4300",
            "2. high": "29.4800",
            "3. low": "27.7600",
            "4. close": "28.7700",
            "5. volume": "96638"
        },
        "2016-03-08": {
            "1. open": "29.7900",
            "2. high": "29.8500",
            "3. low": "28.0200",
            "4. close": "28.7000",
            "5. volume": "212570"
        },
        "2016-03-07": {
            "1. open": "31.3543",
            "2. high": "32.5000",
            "3. low": "29.3100",
            "4. close": "29.7900",
            "5. volume": "198548"
        },
        "2016-03-04": {
            "1. open": "32.9700",
            "2. high": "33.5000",
            "3. low": "31.4200",
            "4. close": "32.3700",
            "5. volume": "164880"
        },
        "2016-03-03": {
            "1. open": "31.0000",
            "2. high": "32.2400",
            "3. low": "30.9500",
            "4. close": "32.1500",
            "5. volume": "398498"
        },
        "2016-03-02": {
            "1. open": "29.8000",
            "2. high": "31.2500",
            "3. low": "29.7500",
            "4. close": "31.1800",
            "5. volume": "218019"
        },
        "2016-03-01": {
            "1. open": "29.9400",
            "2. high": "30.4990",
            "3. low": "29.4100",
            "4. close": "29.8900",
            "5. volume": "176175"
        },
        "2016-02-29": {
            "1. open": "29.5000",
            "2. high": "30.5135",
            "3. low": "28.6800",
            "4. close": "29.2700",
            "5. volume": "246950"
        },
        "2016-02-26": {
            "1. open": "30.2700",
            "2. high": "30.2700",
            "3. low": "28.3800",
            "4. close": "29.7500",
            "5. volume": "131353"
        },
        "2016-02-25": {
            "1. open": "28.4400",
            "2. high": "29.6800",
            "3. low": "27.8000",
            "4. close": "28.9500",
            "5. volume": "206060"
        },
        "2016-02-24": {
            "1. open": "26.5000",
            "2. high": "28.0339",
            "3. low": "26.5000",
            "4. close": "27.8400",
            "5. volume": "76445"
        },
        "2016-02-23": {
            "1. open": "26.7000",
            "2. high": "28.3958",
            "3. low": "26.6400",
            "4. close": "27.1500",
            "5. volume": "269441"
        },
        "2016-02-22": {
            "1. open": "27.0000",
            "2. high": "29.0000",
            "3. low": "27.0000",
            "4. close": "27.4700",
            "5. volume": "106313"
        },
        "2016-02-19": {
            "1. open": "26.0000",
            "2. high": "27.5300",
            "3. low": "25.6000",
            "4. close": "27.0300",
            "5. volume": "159503"
        },
        "2016-02-18": {
            "1. open": "26.9400",
            "2. high": "27.7700",
            "3. low": "25.4100",
            "4. close": "26.6500",
            "5. volume": "283316"
        },
        "2016-02-17": {
            "1. open": "25.4400",
            "2. high": "26.7400",
            "3. low": "24.6003",
            "4. close": "26.0600",
            "5. volume": "244807"
        },
        "2016-02-16": {
            "1. open": "24.5200",
            "2. high": "26.4000",
            "3. low": "23.6000",
            "4. close": "25.1300",
            "5. volume": "228015"
        },
        "2016-02-12": {
            "1. open": "24.0900",
            "2. high": "24.6100",
            "3. low": "23.2000",
            "4. close": "23.9800",
            "5. volume": "128000"
        },
        "2016-02-11": {
            "1. open": "26.4800",
            "2. high": "26.7400",
            "3. low": "22.5100",
            "4. close": "24.1000",
            "5. volume": "497030"
        },
        "2016-02-10": {
            "1. open": "27.9800",
            "2. high": "27.9800",
            "3. low": "25.3000",
            "4. close": "26.8800",
            "5. volume": "469833"
        },
        "2016-02-09": {
            "1. open": "30.8600",
            "2. high": "30.8600",
            "3. low": "27.0000",
            "4. close": "27.6600",
            "5. volume": "360876"
        },
        "2016-02-08": {
            "1. open": "34.0000",
            "2. high": "34.2450",
            "3. low": "31.3700",
            "4. close": "31.5200",
            "5. volume": "102653"
        },
        "2016-02-05": {
            "1. open": "31.3000",
            "2. high": "35.6000",
            "3. low": "30.6300",
            "4. close": "33.9100",
            "5. volume": "376530"
        },
        "2016-02-04": {
            "1. open": "28.1500",
            "2. high": "31.4000",
            "3. low": "27.6100",
            "4. close": "30.5000",
            "5. volume": "361668"
        },
        "2016-02-03": {
            "1. open": "28.9700",
            "2. high": "29.4900",
            "3. low": "27.0500",
            "4. close": "28.3200",
            "5. volume": "2064816"
        }
    }
}